{
  "activation": {
    "blocks_remaining": 5603,
    "current_height": 3422540,
    "estimated_at": "2026-07-28T12:00:00Z",
    "height": 3428143,
    "progress_bps": 998366,
    "reached": false
  },
  "generated_at": "2026-07-23T16:43:58.369465+00:00",
  "health": {
    "chain_status": "synced",
    "last_chain_timestamp": 1784824784,
    "status": "ok",
    "tip_hash": "00000000007dcd348fa73b408d2a390760e5dc08a6a3746e4160fe7734992c09"
  },
  "history": [
    {
      "height": 8475,
      "lockbox": 0,
      "orchard": 0,
      "sapling": 0,
      "sprout": 0,
      "timestamp": 1478868313,
      "transparent": 2245345375000
    },
    {
      "height": 16630,
      "lockbox": 0,
      "orchard": 0,
      "sapling": 0,
      "sprout": 0,
      "timestamp": 1480093685,
      "transparent": 8643962250000
    },
    {
      "height": 24765,
      "lockbox": 0,
      "orchard": 0,
      "sapling": 0,
      "sprout": 0,
      "timestamp": 1481320096,
      "transparent": 18458125000000
    },
    {
      "height": 32882,
      "lockbox": 0,
      "orchard": 0,
      "sapling": 0,
      "sprout": 0,
      "timestamp": 1482543747,
      "transparent": 28604375000000
    },
    {
      "height": 41040,
      "lockbox": 0,
      "orchard": 0,
      "sapling": 0,
      "sprout": 0,
      "timestamp": 1483774868,
      "transparent": 38801875000000
    },
    {
      "height": 49155,
      "lockbox": 0,
      "orchard": 0,
      "sapling": 0,
      "sprout": 0,
      "timestamp": 1484999835,
      "transparent": 48945625000000
    },
    {
      "height": 57324,
      "lockbox": 0,
      "orchard": 0,
      "sapling": 0,
      "sprout": 0,
      "timestamp": 1486232588,
      "transparent": 59156875000000
    },
    {
      "height": 65481,
      "lockbox": 0,
      "orchard": 0,
      "sapling": 0,
      "sprout": 0,
      "timestamp": 1487462744,
      "transparent": 69353125000000
    },
    {
      "height": 73530,
      "lockbox": 0,
      "orchard": 0,
      "sapling": 0,
      "sprout": 0,
      "timestamp": 1488676576,
      "transparent": 79414375000000
    },
    {
      "height": 81804,
      "lockbox": 0,
      "orchard": 0,
      "sapling": 0,
      "sprout": 0,
      "timestamp": 1489925120,
      "transparent": 89756875000000
    },
    {
      "height": 89835,
      "lockbox": 0,
      "orchard": 0,
      "sapling": 0,
      "sprout": 0,
      "timestamp": 1491136496,
      "transparent": 99795625000000
    },
    {
      "height": 98136,
      "lockbox": 0,
      "orchard": 0,
      "sapling": 0,
      "sprout": 0,
      "timestamp": 1492383832,
      "transparent": 110171875000000
    },
    {
      "height": 106218,
      "lockbox": 0,
      "orchard": 0,
      "sapling": 0,
      "sprout": 0,
      "timestamp": 1493602587,
      "transparent": 120274375000000
    },
    {
      "height": 114369,
      "lockbox": 0,
      "orchard": 0,
      "sapling": 0,
      "sprout": 0,
      "timestamp": 1494829150,
      "transparent": 130463125000000
    },
    {
      "height": 122616,
      "lockbox": 0,
      "orchard": 0,
      "sapling": 0,
      "sprout": 0,
      "timestamp": 1496070512,
      "transparent": 140771875000000
    },
    {
      "height": 130726,
      "lockbox": 0,
      "orchard": 0,
      "sapling": 0,
      "sprout": 0,
      "timestamp": 1497292164,
      "transparent": 150909375000000
    },
    {
      "height": 138746,
      "lockbox": 0,
      "orchard": 0,
      "sapling": 0,
      "sprout": 0,
      "timestamp": 1498498580,
      "transparent": 160934375000000
    },
    {
      "height": 147060,
      "lockbox": 0,
      "orchard": 0,
      "sapling": 0,
      "sprout": 0,
      "timestamp": 1499751535,
      "transparent": 171326875000000
    },
    {
      "height": 155194,
      "lockbox": 0,
      "orchard": 0,
      "sapling": 0,
      "sprout": 0,
      "timestamp": 1500977614,
      "transparent": 181494375000000
    },
    {
      "height": 163366,
      "lockbox": 0,
      "orchard": 0,
      "sapling": 0,
      "sprout": 0,
      "timestamp": 1502210178,
      "transparent": 191709375000000
    },
    {
      "height": 171496,
      "lockbox": 0,
      "orchard": 0,
      "sapling": 0,
      "sprout": 0,
      "timestamp": 1503434178,
      "transparent": 201871875000000
    },
    {
      "height": 179670,
      "lockbox": 0,
      "orchard": 0,
      "sapling": 0,
      "sprout": 0,
      "timestamp": 1504666645,
      "transparent": 212089375000000
    },
    {
      "height": 187812,
      "lockbox": 0,
      "orchard": 0,
      "sapling": 0,
      "sprout": 0,
      "timestamp": 1505894564,
      "transparent": 222266875000000
    },
    {
      "height": 195924,
      "lockbox": 0,
      "orchard": 0,
      "sapling": 0,
      "sprout": 0,
      "timestamp": 1507115061,
      "transparent": 232406875000000
    },
    {
      "height": 204006,
      "lockbox": 0,
      "orchard": 0,
      "sapling": 0,
      "sprout": 0,
      "timestamp": 1508334625,
      "transparent": 242509375000000
    },
    {
      "height": 212217,
      "lockbox": 0,
      "orchard": 0,
      "sapling": 0,
      "sprout": 0,
      "timestamp": 1509574933,
      "transparent": 252773125000000
    },
    {
      "height": 220350,
      "lockbox": 0,
      "orchard": 0,
      "sapling": 0,
      "sprout": 0,
      "timestamp": 1510802356,
      "transparent": 262939375000000
    },
    {
      "height": 228570,
      "lockbox": 0,
      "orchard": 0,
      "sapling": 0,
      "sprout": 0,
      "timestamp": 1512042073,
      "transparent": 273214375000000
    },
    {
      "height": 236739,
      "lockbox": 0,
      "orchard": 0,
      "sapling": 0,
      "sprout": 0,
      "timestamp": 1513273281,
      "transparent": 283425625000000
    },
    {
      "height": 244610,
      "lockbox": 0,
      "orchard": 0,
      "sapling": 0,
      "sprout": 0,
      "timestamp": 1514461013,
      "transparent": 293264375000000
    },
    {
      "height": 252900,
      "lockbox": 0,
      "orchard": 0,
      "sapling": 0,
      "sprout": 0,
      "timestamp": 1515711863,
      "transparent": 303626875000000
    },
    {
      "height": 261171,
      "lockbox": 0,
      "orchard": 0,
      "sapling": 0,
      "sprout": 0,
      "timestamp": 1516957634,
      "transparent": 313965625000000
    },
    {
      "height": 269113,
      "lockbox": 0,
      "orchard": 0,
      "sapling": 0,
      "sprout": 0,
      "timestamp": 1518154761,
      "transparent": 323893125000000
    },
    {
      "height": 277492,
      "lockbox": 0,
      "orchard": 0,
      "sapling": 0,
      "sprout": 0,
      "timestamp": 1519417673,
      "transparent": 334366875000000
    },
    {
      "height": 285623,
      "lockbox": 0,
      "orchard": 0,
      "sapling": 0,
      "sprout": 0,
      "timestamp": 1520643204,
      "transparent": 344530625000000
    },
    {
      "height": 293604,
      "lockbox": 0,
      "orchard": 0,
      "sapling": 0,
      "sprout": 0,
      "timestamp": 1521847708,
      "transparent": 354506875000000
    },
    {
      "height": 301794,
      "lockbox": 0,
      "orchard": 0,
      "sapling": 0,
      "sprout": 0,
      "timestamp": 1523084124,
      "transparent": 364744375000000
    },
    {
      "height": 310062,
      "lockbox": 0,
      "orchard": 0,
      "sapling": 0,
      "sprout": 0,
      "timestamp": 1524331039,
      "transparent": 375079375000000
    },
    {
      "height": 318096,
      "lockbox": 0,
      "orchard": 0,
      "sapling": 0,
      "sprout": 0,
      "timestamp": 1525544673,
      "transparent": 385121875000000
    },
    {
      "height": 326232,
      "lockbox": 0,
      "orchard": 0,
      "sapling": 0,
      "sprout": 0,
      "timestamp": 1526770473,
      "transparent": 395291875000000
    },
    {
      "height": 334512,
      "lockbox": 0,
      "orchard": 0,
      "sapling": 0,
      "sprout": 0,
      "timestamp": 1528018980,
      "transparent": 405641875000000
    },
    {
      "height": 342578,
      "lockbox": 0,
      "orchard": 0,
      "sapling": 0,
      "sprout": 0,
      "timestamp": 1529233255,
      "transparent": 415724375000000
    },
    {
      "height": 350688,
      "lockbox": 0,
      "orchard": 0,
      "sapling": 0,
      "sprout": 0,
      "timestamp": 1530454987,
      "transparent": 425861875000000
    },
    {
      "height": 358704,
      "lockbox": 0,
      "orchard": 0,
      "sapling": 0,
      "sprout": 0,
      "timestamp": 1531664578,
      "transparent": 435881875000000
    },
    {
      "height": 367005,
      "lockbox": 0,
      "orchard": 0,
      "sapling": 0,
      "sprout": 0,
      "timestamp": 1532915886,
      "transparent": 446258125000000
    },
    {
      "height": 375180,
      "lockbox": 0,
      "orchard": 0,
      "sapling": 0,
      "sprout": 0,
      "timestamp": 1534147622,
      "transparent": 456476875000000
    },
    {
      "height": 383410,
      "lockbox": 0,
      "orchard": 0,
      "sapling": 0,
      "sprout": 0,
      "timestamp": 1535388066,
      "transparent": 466764375000000
    },
    {
      "height": 391590,
      "lockbox": 0,
      "orchard": 0,
      "sapling": 0,
      "sprout": 0,
      "timestamp": 1536619378,
      "transparent": 476989375000000
    },
    {
      "height": 399602,
      "lockbox": 0,
      "orchard": 0,
      "sapling": 0,
      "sprout": 0,
      "timestamp": 1537824641,
      "transparent": 487004375000000
    },
    {
      "height": 407797,
      "lockbox": 0,
      "orchard": 0,
      "sapling": 0,
      "sprout": 0,
      "timestamp": 1539058531,
      "transparent": 497248125000000
    },
    {
      "height": 416052,
      "lockbox": 0,
      "orchard": 0,
      "sapling": 0,
      "sprout": 0,
      "timestamp": 1540304091,
      "transparent": 507566875000000
    },
    {
      "height": 424190,
      "lockbox": 0,
      "orchard": 0,
      "sapling": 2233095381575,
      "sprout": 0,
      "timestamp": 1541529176,
      "transparent": 515506279618425
    },
    {
      "height": 432380,
      "lockbox": 0,
      "orchard": 0,
      "sapling": 2565885737181,
      "sprout": 0,
      "timestamp": 1542763369,
      "transparent": 525410989262819
    },
    {
      "height": 440496,
      "lockbox": 0,
      "orchard": 0,
      "sapling": 2865003287188,
      "sprout": 0,
      "timestamp": 1543987936,
      "transparent": 535256871712812
    },
    {
      "height": 448528,
      "lockbox": 0,
      "orchard": 0,
      "sapling": 3351342288359,
      "sprout": 0,
      "timestamp": 1545197827,
      "transparent": 544810532711641
    },
    {
      "height": 456840,
      "lockbox": 0,
      "orchard": 0,
      "sapling": 4096376492760,
      "sprout": 0,
      "timestamp": 1546449797,
      "transparent": 554455498507240
    },
    {
      "height": 464919,
      "lockbox": 0,
      "orchard": 0,
      "sapling": 4198045960810,
      "sprout": 0,
      "timestamp": 1547668187,
      "transparent": 564452579039190
    },
    {
      "height": 472920,
      "lockbox": 0,
      "orchard": 0,
      "sapling": 6259196543156,
      "sprout": 0,
      "timestamp": 1548872511,
      "transparent": 572392678456844
    },
    {
      "height": 481248,
      "lockbox": 0,
      "orchard": 0,
      "sapling": 11408057732401,
      "sprout": 0,
      "timestamp": 1550129537,
      "transparent": 577653817267599
    },
    {
      "height": 489220,
      "lockbox": 0,
      "orchard": 0,
      "sapling": 12520018388499,
      "sprout": 0,
      "timestamp": 1551331247,
      "transparent": 586506856611501
    },
    {
      "height": 497448,
      "lockbox": 0,
      "orchard": 0,
      "sapling": 12124142352489,
      "sprout": 0,
      "timestamp": 1552570612,
      "transparent": 597187732647511
    },
    {
      "height": 505552,
      "lockbox": 0,
      "orchard": 0,
      "sapling": 12347611478528,
      "sprout": 0,
      "timestamp": 1553791580,
      "transparent": 607094263521472
    },
    {
      "height": 513867,
      "lockbox": 0,
      "orchard": 0,
      "sapling": 12208935204724,
      "sprout": 0,
      "timestamp": 1555045561,
      "transparent": 617626689795276
    },
    {
      "height": 522060,
      "lockbox": 0,
      "orchard": 0,
      "sapling": 12407531983813,
      "sprout": 0,
      "timestamp": 1556279008,
      "transparent": 627669343016187
    },
    {
      "height": 530122,
      "lockbox": 0,
      "orchard": 0,
      "sapling": 12316354265986,
      "sprout": 0,
      "timestamp": 1557492598,
      "transparent": 637838020734014
    },
    {
      "height": 538226,
      "lockbox": 0,
      "orchard": 0,
      "sapling": 12663484762801,
      "sprout": 0,
      "timestamp": 1558714789,
      "transparent": 647620890237199
    },
    {
      "height": 546516,
      "lockbox": 0,
      "orchard": 0,
      "sapling": 12869196044768,
      "sprout": 0,
      "timestamp": 1559963996,
      "transparent": 657777678955232
    },
    {
      "height": 554320,
      "lockbox": 0,
      "orchard": 0,
      "sapling": 19961629097060,
      "sprout": 0,
      "timestamp": 1561141435,
      "transparent": 660440245902940
    },
    {
      "height": 562770,
      "lockbox": 0,
      "orchard": 0,
      "sapling": 20577094792404,
      "sprout": 0,
      "timestamp": 1562414459,
      "transparent": 670387280207596
    },
    {
      "height": 570882,
      "lockbox": 0,
      "orchard": 0,
      "sapling": 22540671130380,
      "sprout": 0,
      "timestamp": 1563637303,
      "transparent": 678563703869620
    },
    {
      "height": 579044,
      "lockbox": 0,
      "orchard": 0,
      "sapling": 20973331490935,
      "sprout": 0,
      "timestamp": 1564867189,
      "transparent": 690333543509065
    },
    {
      "height": 587208,
      "lockbox": 0,
      "orchard": 0,
      "sapling": 20365308032159,
      "sprout": 0,
      "timestamp": 1566097971,
      "transparent": 701146566967841
    },
    {
      "height": 595354,
      "lockbox": 0,
      "orchard": 0,
      "sapling": 20256789501811,
      "sprout": 0,
      "timestamp": 1567324968,
      "transparent": 711437585498189
    },
    {
      "height": 603588,
      "lockbox": 0,
      "orchard": 0,
      "sapling": 20305478676449,
      "sprout": 0,
      "timestamp": 1568565099,
      "transparent": 721681396323551
    },
    {
      "height": 611586,
      "lockbox": 0,
      "orchard": 0,
      "sapling": 21647105890185,
      "sprout": 0,
      "timestamp": 1569770849,
      "transparent": 730337269109815
    },
    {
      "height": 619892,
      "lockbox": 0,
      "orchard": 0,
      "sapling": 22788254011036,
      "sprout": 0,
      "timestamp": 1571021427,
      "transparent": 739578620988964
    },
    {
      "height": 627966,
      "lockbox": 0,
      "orchard": 0,
      "sapling": 22193686949957,
      "sprout": 0,
      "timestamp": 1572238095,
      "transparent": 750265688050043
    },
    {
      "height": 636192,
      "lockbox": 0,
      "orchard": 0,
      "sapling": 21006057456151,
      "sprout": 0,
      "timestamp": 1573478332,
      "transparent": 761735817543849
    },
    {
      "height": 644184,
      "lockbox": 0,
      "orchard": 0,
      "sapling": 21274847997825,
      "sprout": 0,
      "timestamp": 1574682567,
      "transparent": 771457027002175
    },
    {
      "height": 652482,
      "lockbox": 0,
      "orchard": 0,
      "sapling": 23530628300721,
      "sprout": 0,
      "timestamp": 1575934485,
      "transparent": 779573746699279
    },
    {
      "height": 667656,
      "lockbox": 0,
      "orchard": 0,
      "sapling": 25962107848198,
      "sprout": 0,
      "timestamp": 1577161027,
      "transparent": 787324142151802
    },
    {
      "height": 684045,
      "lockbox": 0,
      "orchard": 0,
      "sapling": 27451629562029,
      "sprout": 0,
      "timestamp": 1578396393,
      "transparent": 796077745437971
    },
    {
      "height": 700149,
      "lockbox": 0,
      "orchard": 0,
      "sapling": 25307184466744,
      "sprout": 0,
      "timestamp": 1579609170,
      "transparent": 808287190533256
    },
    {
      "height": 716560,
      "lockbox": 0,
      "orchard": 0,
      "sapling": 28261289866698,
      "sprout": 0,
      "timestamp": 1580845918,
      "transparent": 815589960133302
    },
    {
      "height": 732636,
      "lockbox": 0,
      "orchard": 0,
      "sapling": 27757302475302,
      "sprout": 0,
      "timestamp": 1582057420,
      "transparent": 826141447524698
    },
    {
      "height": 749190,
      "lockbox": 0,
      "orchard": 0,
      "sapling": 26576119007301,
      "sprout": 0,
      "timestamp": 1583305074,
      "transparent": 837668880992699
    },
    {
      "height": 765570,
      "lockbox": 0,
      "orchard": 0,
      "sapling": 26230652319952,
      "sprout": 0,
      "timestamp": 1584539099,
      "transparent": 848251847680048
    },
    {
      "height": 781823,
      "lockbox": 0,
      "orchard": 0,
      "sapling": 28449148670851,
      "sprout": 0,
      "timestamp": 1585764968,
      "transparent": 856191476329149
    },
    {
      "height": 798192,
      "lockbox": 0,
      "orchard": 0,
      "sapling": 28173466887551,
      "sprout": 0,
      "timestamp": 1586998189,
      "transparent": 866697783112449
    },
    {
      "height": 814338,
      "lockbox": 0,
      "orchard": 0,
      "sapling": 31414959561441,
      "sprout": 0,
      "timestamp": 1588213942,
      "transparent": 873547540438559
    },
    {
      "height": 830772,
      "lockbox": 0,
      "orchard": 0,
      "sapling": 32524221698085,
      "sprout": 0,
      "timestamp": 1589452371,
      "transparent": 882709528301915
    },
    {
      "height": 846963,
      "lockbox": 0,
      "orchard": 0,
      "sapling": 32908773532960,
      "sprout": 0,
      "timestamp": 1590673390,
      "transparent": 892444351467040
    },
    {
      "height": 863232,
      "lockbox": 0,
      "orchard": 0,
      "sapling": 34916394571755,
      "sprout": 0,
      "timestamp": 1591899241,
      "transparent": 900604855428245
    },
    {
      "height": 879727,
      "lockbox": 0,
      "orchard": 0,
      "sapling": 42932602099316,
      "sprout": 0,
      "timestamp": 1593141986,
      "transparent": 902898022900684
    },
    {
      "height": 895896,
      "lockbox": 0,
      "orchard": 0,
      "sapling": 43161173310500,
      "sprout": 0,
      "timestamp": 1594360941,
      "transparent": 912775076689500
    },
    {
      "height": 912126,
      "lockbox": 0,
      "orchard": 0,
      "sapling": 39769988605807,
      "sprout": 0,
      "timestamp": 1595584350,
      "transparent": 926310011394193
    },
    {
      "height": 928608,
      "lockbox": 0,
      "orchard": 0,
      "sapling": 43602521369403,
      "sprout": 0,
      "timestamp": 1596826376,
      "transparent": 932778728630597
    },
    {
      "height": 944877,
      "lockbox": 0,
      "orchard": 0,
      "sapling": 40697471778481,
      "sprout": 0,
      "timestamp": 1598052971,
      "transparent": 945851903221519
    },
    {
      "height": 961214,
      "lockbox": 0,
      "orchard": 0,
      "sapling": 36450774433516,
      "sprout": 0,
      "timestamp": 1599283374,
      "transparent": 960309225566484
    },
    {
      "height": 977535,
      "lockbox": 0,
      "orchard": 0,
      "sapling": 46936480897884,
      "sprout": 0,
      "timestamp": 1600513613,
      "transparent": 960024144102116
    },
    {
      "height": 993720,
      "lockbox": 0,
      "orchard": 0,
      "sapling": 45155194930913,
      "sprout": 0,
      "timestamp": 1601733462,
      "transparent": 971921055069087
    },
    {
      "height": 1010124,
      "lockbox": 0,
      "orchard": 0,
      "sapling": 54085296171636,
      "sprout": 0,
      "timestamp": 1602969757,
      "transparent": 973243453828364
    },
    {
      "height": 1026071,
      "lockbox": 0,
      "orchard": 0,
      "sapling": 49312988245914,
      "sprout": 0,
      "timestamp": 1604171214,
      "transparent": 987982636754086
    },
    {
      "height": 1042730,
      "lockbox": 0,
      "orchard": 0,
      "sapling": 53718724267038,
      "sprout": 0,
      "timestamp": 1605426852,
      "transparent": 993988775732962
    },
    {
      "height": 1059003,
      "lockbox": 0,
      "orchard": 0,
      "sapling": 56059545408197,
      "sprout": 0,
      "timestamp": 1606653838,
      "transparent": 997879829591803
    },
    {
      "height": 1075215,
      "lockbox": 0,
      "orchard": 0,
      "sapling": 61461263650083,
      "sprout": 0,
      "timestamp": 1607876356,
      "transparent": 997544361349917
    },
    {
      "height": 1091638,
      "lockbox": 0,
      "orchard": 0,
      "sapling": 62057972746811,
      "sprout": 0,
      "timestamp": 1609114462,
      "transparent": 1002079839753189
    },
    {
      "height": 1107873,
      "lockbox": 0,
      "orchard": 0,
      "sapling": 60234041456626,
      "sprout": 0,
      "timestamp": 1610339089,
      "transparent": 1008977208543374
    },
    {
      "height": 1124188,
      "lockbox": 0,
      "orchard": 0,
      "sapling": 62425497637771,
      "sprout": 0,
      "timestamp": 1611569428,
      "transparent": 1011884189862229
    },
    {
      "height": 1140444,
      "lockbox": 0,
      "orchard": 0,
      "sapling": 62335864530831,
      "sprout": 0,
      "timestamp": 1612795506,
      "transparent": 1017053822969169
    },
    {
      "height": 1156596,
      "lockbox": 0,
      "orchard": 0,
      "sapling": 59388079919461,
      "sprout": 0,
      "timestamp": 1614013237,
      "transparent": 1025049107580539
    },
    {
      "height": 1173060,
      "lockbox": 0,
      "orchard": 0,
      "sapling": 57787694646731,
      "sprout": 0,
      "timestamp": 1615255504,
      "transparent": 1031794492853269
    },
    {
      "height": 1189366,
      "lockbox": 0,
      "orchard": 0,
      "sapling": 59028848834144,
      "sprout": 0,
      "timestamp": 1616484642,
      "transparent": 1035648963665856
    },
    {
      "height": 1205724,
      "lockbox": 0,
      "orchard": 0,
      "sapling": 59007167343215,
      "sprout": 0,
      "timestamp": 1617716845,
      "transparent": 1040782520156785
    },
    {
      "height": 1221911,
      "lockbox": 0,
      "orchard": 0,
      "sapling": 57284281282146,
      "sprout": 0,
      "timestamp": 1618937636,
      "transparent": 1047563843717854
    },
    {
      "height": 1238288,
      "lockbox": 0,
      "orchard": 0,
      "sapling": 56217113131934,
      "sprout": 0,
      "timestamp": 1620174009,
      "transparent": 1053748824368066
    },
    {
      "height": 1254384,
      "lockbox": 0,
      "orchard": 0,
      "sapling": 55339818020662,
      "sprout": 0,
      "timestamp": 1621387862,
      "transparent": 1059656119479338
    },
    {
      "height": 1270692,
      "lockbox": 0,
      "orchard": 0,
      "sapling": 57757525051080,
      "sprout": 0,
      "timestamp": 1622618125,
      "transparent": 1062334662448920
    },
    {
      "height": 1287078,
      "lockbox": 0,
      "orchard": 0,
      "sapling": 65892499076859,
      "sprout": 0,
      "timestamp": 1623855067,
      "transparent": 1059320313423141
    },
    {
      "height": 1303380,
      "lockbox": 0,
      "orchard": 0,
      "sapling": 65636646097210,
      "sprout": 0,
      "timestamp": 1625084243,
      "transparent": 1064670541402790
    },
    {
      "height": 1319694,
      "lockbox": 0,
      "orchard": 0,
      "sapling": 66134125896174,
      "sprout": 0,
      "timestamp": 1626314243,
      "transparent": 1069271186603826
    },
    {
      "height": 1335999,
      "lockbox": 0,
      "orchard": 0,
      "sapling": 66659800774252,
      "sprout": 0,
      "timestamp": 1627543545,
      "transparent": 1073840824225748
    },
    {
      "height": 1352182,
      "lockbox": 0,
      "orchard": 0,
      "sapling": 69485967215977,
      "sprout": 0,
      "timestamp": 1628764578,
      "transparent": 1076071845284023
    },
    {
      "height": 1368607,
      "lockbox": 0,
      "orchard": 0,
      "sapling": 82242264828186,
      "sprout": 0,
      "timestamp": 1630003376,
      "transparent": 1068448360171814
    },
    {
      "height": 1384815,
      "lockbox": 0,
      "orchard": 0,
      "sapling": 84341821241622,
      "sprout": 0,
      "timestamp": 1631226604,
      "transparent": 1071413803758378
    },
    {
      "height": 1401094,
      "lockbox": 0,
      "orchard": 0,
      "sapling": 85879023210183,
      "sprout": 0,
      "timestamp": 1632454557,
      "transparent": 1074963789289817
    },
    {
      "height": 1417134,
      "lockbox": 0,
      "orchard": 0,
      "sapling": 86853446708816,
      "sprout": 0,
      "timestamp": 1633664741,
      "transparent": 1079001865791184
    },
    {
      "height": 1433718,
      "lockbox": 0,
      "orchard": 0,
      "sapling": 89138177255587,
      "sprout": 0,
      "timestamp": 1634914890,
      "transparent": 1081899635244413
    },
    {
      "height": 1450044,
      "lockbox": 0,
      "orchard": 0,
      "sapling": 91044580642997,
      "sprout": 0,
      "timestamp": 1636146559,
      "transparent": 1085095106857003
    },
    {
      "height": 1466313,
      "lockbox": 0,
      "orchard": 0,
      "sapling": 85043726744959,
      "sprout": 0,
      "timestamp": 1637374390,
      "transparent": 1096180023255041
    },
    {
      "height": 1482598,
      "lockbox": 0,
      "orchard": 0,
      "sapling": 78239529857803,
      "sprout": 0,
      "timestamp": 1638600889,
      "transparent": 1108073282642197
    },
    {
      "height": 1498941,
      "lockbox": 0,
      "orchard": 0,
      "sapling": 81472614170946,
      "sprout": 0,
      "timestamp": 1639833522,
      "transparent": 1109947385829054
    },
    {
      "height": 1515240,
      "lockbox": 0,
      "orchard": 0,
      "sapling": 83888572096841,
      "sprout": 0,
      "timestamp": 1641062360,
      "transparent": 1112624865403159
    },
    {
      "height": 1531260,
      "lockbox": 0,
      "orchard": 0,
      "sapling": 79935404608565,
      "sprout": 0,
      "timestamp": 1642269135,
      "transparent": 1121584282891435
    },
    {
      "height": 1547748,
      "lockbox": 0,
      "orchard": 0,
      "sapling": 67888003466526,
      "sprout": 0,
      "timestamp": 1643513269,
      "transparent": 1138784184033474
    },
    {
      "height": 1564056,
      "lockbox": 0,
      "orchard": 0,
      "sapling": 69648375097558,
      "sprout": 0,
      "timestamp": 1644742708,
      "transparent": 1142120062402442
    },
    {
      "height": 1580384,
      "lockbox": 0,
      "orchard": 0,
      "sapling": 71501613893289,
      "sprout": 0,
      "timestamp": 1645973304,
      "transparent": 1145369323606711
    },
    {
      "height": 1596729,
      "lockbox": 0,
      "orchard": 0,
      "sapling": 68691115455387,
      "sprout": 0,
      "timestamp": 1647204287,
      "transparent": 1153287634544613
    },
    {
      "height": 1613027,
      "lockbox": 0,
      "orchard": 0,
      "sapling": 71236822340307,
      "sprout": 0,
      "timestamp": 1648433787,
      "transparent": 1155835052659693
    },
    {
      "height": 1629225,
      "lockbox": 0,
      "orchard": 0,
      "sapling": 71992907794184,
      "sprout": 0,
      "timestamp": 1649654757,
      "transparent": 1160140842205816
    },
    {
      "height": 1645548,
      "lockbox": 0,
      "orchard": 0,
      "sapling": 76439381893326,
      "sprout": 0,
      "timestamp": 1650884728,
      "transparent": 1160795305606674
    },
    {
      "height": 1661544,
      "lockbox": 0,
      "orchard": 0,
      "sapling": 76199310721597,
      "sprout": 0,
      "timestamp": 1652091656,
      "transparent": 1166034126778403
    },
    {
      "height": 1678170,
      "lockbox": 0,
      "orchard": 0,
      "sapling": 78118853604015,
      "sprout": 0,
      "timestamp": 1653345288,
      "transparent": 1169310208895985
    },
    {
      "height": 1694485,
      "lockbox": 0,
      "orchard": 524033591293,
      "sapling": 79662694674415,
      "sprout": 0,
      "timestamp": 1654575335,
      "transparent": 1172340771734292
    },
    {
      "height": 1710648,
      "lockbox": 0,
      "orchard": 949739758786,
      "sapling": 79784138656718,
      "sprout": 0,
      "timestamp": 1655794174,
      "transparent": 1176844559084496
    },
    {
      "height": 1727100,
      "lockbox": 0,
      "orchard": 952087808107,
      "sapling": 79608051899028,
      "sprout": 0,
      "timestamp": 1657035055,
      "transparent": 1182159547792865
    },
    {
      "height": 1743324,
      "lockbox": 0,
      "orchard": 999330606646,
      "sapling": 79073947802843,
      "sprout": 0,
      "timestamp": 1658258400,
      "transparent": 1187716409090511
    },
    {
      "height": 1759680,
      "lockbox": 0,
      "orchard": 999932903399,
      "sapling": 78921724572038,
      "sprout": 0,
      "timestamp": 1659492035,
      "transparent": 1192979280024563
    },
    {
      "height": 1775973,
      "lockbox": 0,
      "orchard": 1122014397325,
      "sapling": 78611185152716,
      "sprout": 0,
      "timestamp": 1660719665,
      "transparent": 1198259300449959
    },
    {
      "height": 1792218,
      "lockbox": 0,
      "orchard": 1154539704196,
      "sapling": 81072042037993,
      "sprout": 0,
      "timestamp": 1661943196,
      "transparent": 1200842480757811
    },
    {
      "height": 1808586,
      "lockbox": 0,
      "orchard": 1560662201974,
      "sapling": 83409610824883,
      "sprout": 0,
      "timestamp": 1663176731,
      "transparent": 1203213789473143
    },
    {
      "height": 1824912,
      "lockbox": 0,
      "orchard": 1515932570731,
      "sapling": 85881424765591,
      "sprout": 0,
      "timestamp": 1664407624,
      "transparent": 1205888580163678
    },
    {
      "height": 1841112,
      "lockbox": 0,
      "orchard": 1449773393070,
      "sapling": 86517322030878,
      "sprout": 0,
      "timestamp": 1665628726,
      "transparent": 1210381342076052
    },
    {
      "height": 1857375,
      "lockbox": 0,
      "orchard": 1486121558340,
      "sapling": 90729802630176,
      "sprout": 0,
      "timestamp": 1666854182,
      "transparent": 1211214700811484
    },
    {
      "height": 1873764,
      "lockbox": 0,
      "orchard": 1613428430309,
      "sapling": 89809045883211,
      "sprout": 0,
      "timestamp": 1668088963,
      "transparent": 1217129713186480
    },
    {
      "height": 1890006,
      "lockbox": 0,
      "orchard": 1907099240734,
      "sapling": 92974235715023,
      "sprout": 0,
      "timestamp": 1669312891,
      "transparent": 1218746477544243
    },
    {
      "height": 1906320,
      "lockbox": 0,
      "orchard": 2053565076344,
      "sapling": 93520632183570,
      "sprout": 0,
      "timestamp": 1670542222,
      "transparent": 1223151740240086
    },
    {
      "height": 1922734,
      "lockbox": 0,
      "orchard": 2850034707674,
      "sapling": 95073837507565,
      "sprout": 0,
      "timestamp": 1671778802,
      "transparent": 1225931440284761
    },
    {
      "height": 1939058,
      "lockbox": 0,
      "orchard": 2717132192711,
      "sapling": 98893552680855,
      "sprout": 0,
      "timestamp": 1673009241,
      "transparent": 1227345877626434
    },
    {
      "height": 1955330,
      "lockbox": 0,
      "orchard": 2696276575053,
      "sapling": 101086654942125,
      "sprout": 0,
      "timestamp": 1674235854,
      "transparent": 1230258630982822
    },
    {
      "height": 1971630,
      "lockbox": 0,
      "orchard": 3068067736998,
      "sapling": 101052555275486,
      "sprout": 0,
      "timestamp": 1675465005,
      "transparent": 1235014689487516
    },
    {
      "height": 1987953,
      "lockbox": 0,
      "orchard": 4056254600925,
      "sapling": 97067237080521,
      "sprout": 0,
      "timestamp": 1676694635,
      "transparent": 1243112758318554
    },
    {
      "height": 2004120,
      "lockbox": 0,
      "orchard": 4503508887495,
      "sapling": 98697749880557,
      "sprout": 0,
      "timestamp": 1677913683,
      "transparent": 1246087178731948
    },
    {
      "height": 2020545,
      "lockbox": 0,
      "orchard": 4696881158357,
      "sapling": 102231770570514,
      "sprout": 0,
      "timestamp": 1679151273,
      "transparent": 1247492598271129
    },
    {
      "height": 2036788,
      "lockbox": 0,
      "orchard": 5432959681350,
      "sapling": 101297102584685,
      "sprout": 0,
      "timestamp": 1680376343,
      "transparent": 1252767125233965
    },
    {
      "height": 2053005,
      "lockbox": 0,
      "orchard": 5852935242347,
      "sapling": 111765936069857,
      "sprout": 0,
      "timestamp": 1681598143,
      "transparent": 1246946128687796
    },
    {
      "height": 2069316,
      "lockbox": 0,
      "orchard": 7041668829401,
      "sapling": 121106881313271,
      "sprout": 0,
      "timestamp": 1682828457,
      "transparent": 1241513637357328
    },
    {
      "height": 2085582,
      "lockbox": 0,
      "orchard": 7828595445292,
      "sapling": 119613600150612,
      "sprout": 0,
      "timestamp": 1684054786,
      "transparent": 1247303116904096
    },
    {
      "height": 2102032,
      "lockbox": 0,
      "orchard": 8541495983487,
      "sapling": 116267952668598,
      "sprout": 0,
      "timestamp": 1685294752,
      "transparent": 1255076488847915
    },
    {
      "height": 2118233,
      "lockbox": 0,
      "orchard": 9036044832812,
      "sapling": 118008485564054,
      "sprout": 0,
      "timestamp": 1686515947,
      "transparent": 1257904219603134
    },
    {
      "height": 2134584,
      "lockbox": 0,
      "orchard": 9641226383771,
      "sapling": 122113223188881,
      "sprout": 0,
      "timestamp": 1687748543,
      "transparent": 1258303987927348
    },
    {
      "height": 2150955,
      "lockbox": 0,
      "orchard": 9160791988090,
      "sapling": 118665675082908,
      "sprout": 0,
      "timestamp": 1688982320,
      "transparent": 1267347907929002
    },
    {
      "height": 2167100,
      "lockbox": 0,
      "orchard": 9170562277151,
      "sapling": 116277213241500,
      "sprout": 0,
      "timestamp": 1690200000,
      "transparent": 1274771911981349
    },
    {
      "height": 2183519,
      "lockbox": 0,
      "orchard": 9540588469117,
      "sapling": 114268121051853,
      "sprout": 0,
      "timestamp": 1691438433,
      "transparent": 1281541915479030
    },
    {
      "height": 2199766,
      "lockbox": 0,
      "orchard": 9550479116539,
      "sapling": 113100649504532,
      "sprout": 0,
      "timestamp": 1692662962,
      "transparent": 1287776683878929
    },
    {
      "height": 2215968,
      "lockbox": 0,
      "orchard": 11294095786033,
      "sapling": 114262119724047,
      "sprout": 0,
      "timestamp": 1693884421,
      "transparent": 1289934721989920
    },
    {
      "height": 2232315,
      "lockbox": 0,
      "orchard": 13075857741772,
      "sapling": 113158229824000,
      "sprout": 0,
      "timestamp": 1695117672,
      "transparent": 1294365287434228
    },
    {
      "height": 2248668,
      "lockbox": 0,
      "orchard": 15976926948430,
      "sapling": 112102643843730,
      "sprout": 0,
      "timestamp": 1696349287,
      "transparent": 1297630116707840
    },
    {
      "height": 2265006,
      "lockbox": 0,
      "orchard": 15731702317578,
      "sapling": 112226442225584,
      "sprout": 0,
      "timestamp": 1697581713,
      "transparent": 1302857167956838
    },
    {
      "height": 2281158,
      "lockbox": 0,
      "orchard": 15994235487262,
      "sapling": 113694722930671,
      "sprout": 0,
      "timestamp": 1698799750,
      "transparent": 1306173854082067
    },
    {
      "height": 2297625,
      "lockbox": 0,
      "orchard": 15959188636573,
      "sapling": 110842436187200,
      "sprout": 0,
      "timestamp": 1700040424,
      "transparent": 1314207125176227
    },
    {
      "height": 2313930,
      "lockbox": 0,
      "orchard": 16210570251287,
      "sapling": 112524909035037,
      "sprout": 0,
      "timestamp": 1701269534,
      "transparent": 1317368583213676
    },
    {
      "height": 2330055,
      "lockbox": 0,
      "orchard": 16462378390993,
      "sapling": 111255628996126,
      "sprout": 0,
      "timestamp": 1702485922,
      "transparent": 1323425117612881
    },
    {
      "height": 2346527,
      "lockbox": 0,
      "orchard": 16408823327399,
      "sapling": 109063243656474,
      "sprout": 0,
      "timestamp": 1703727254,
      "transparent": 1330818558016127
    },
    {
      "height": 2362830,
      "lockbox": 0,
      "orchard": 14468641244741,
      "sapling": 108800099210169,
      "sprout": 0,
      "timestamp": 1704955967,
      "transparent": 1338116572045090
    },
    {
      "height": 2379143,
      "lockbox": 0,
      "orchard": 13407242118734,
      "sapling": 109905858989246,
      "sprout": 0,
      "timestamp": 1706185373,
      "transparent": 1343170023892020
    },
    {
      "height": 2395035,
      "lockbox": 0,
      "orchard": 13288853817002,
      "sapling": 109852422652515,
      "sprout": 0,
      "timestamp": 1707383366,
      "transparent": 1348308098530483
    },
    {
      "height": 2411630,
      "lockbox": 0,
      "orchard": 13198076999379,
      "sapling": 110141533162248,
      "sprout": 0,
      "timestamp": 1708634329,
      "transparent": 1353295702338373
    },
    {
      "height": 2428020,
      "lockbox": 0,
      "orchard": 13760915275781,
      "sapling": 103173385829094,
      "sprout": 0,
      "timestamp": 1709869316,
      "transparent": 1364822886395125
    },
    {
      "height": 2444256,
      "lockbox": 0,
      "orchard": 19975169326719,
      "sapling": 103432191555963,
      "sprout": 0,
      "timestamp": 1711094812,
      "transparent": 1363423576617318
    },
    {
      "height": 2460640,
      "lockbox": 0,
      "orchard": 19255167953156,
      "sapling": 106481349386271,
      "sprout": 0,
      "timestamp": 1712328335,
      "transparent": 1366214420160573
    },
    {
      "height": 2476857,
      "lockbox": 0,
      "orchard": 18779050062170,
      "sapling": 106558291140583,
      "sprout": 0,
      "timestamp": 1713551944,
      "transparent": 1371681408797247
    },
    {
      "height": 2493192,
      "lockbox": 0,
      "orchard": 19761047735651,
      "sapling": 105151385383000,
      "sprout": 0,
      "timestamp": 1714782876,
      "transparent": 1377211004381349
    },
    {
      "height": 2509520,
      "lockbox": 0,
      "orchard": 21318800937599,
      "sapling": 104206984867854,
      "sprout": 0,
      "timestamp": 1716014194,
      "transparent": 1381700151694547
    },
    {
      "height": 2525670,
      "lockbox": 0,
      "orchard": 34110516054558,
      "sapling": 106982750321874,
      "sprout": 0,
      "timestamp": 1717231799,
      "transparent": 1371179546123568
    },
    {
      "height": 2542006,
      "lockbox": 0,
      "orchard": 37634685273308,
      "sapling": 106409556650899,
      "sprout": 0,
      "timestamp": 1718463029,
      "transparent": 1373333570575793
    },
    {
      "height": 2558304,
      "lockbox": 0,
      "orchard": 40073621644026,
      "sapling": 104386112316052,
      "sprout": 0,
      "timestamp": 1719692126,
      "transparent": 1378011203539922
    },
    {
      "height": 2574705,
      "lockbox": 0,
      "orchard": 65238717418110,
      "sapling": 101040373321273,
      "sprout": 0,
      "timestamp": 1720928398,
      "transparent": 1361317159260617
    },
    {
      "height": 2590954,
      "lockbox": 0,
      "orchard": 50788782223535,
      "sapling": 98587962319357,
      "sprout": 0,
      "timestamp": 1722152351,
      "transparent": 1383297317957108
    },
    {
      "height": 2607293,
      "lockbox": 0,
      "orchard": 42502706881070,
      "sapling": 96293911217649,
      "sprout": 0,
      "timestamp": 1723383439,
      "transparent": 1398983381901281
    },
    {
      "height": 2623559,
      "lockbox": 0,
      "orchard": 47302042786566,
      "sapling": 94134043681579,
      "sprout": 0,
      "timestamp": 1724610014,
      "transparent": 1401427038531855
    },
    {
      "height": 2639907,
      "lockbox": 0,
      "orchard": 51521233196136,
      "sapling": 96057222284366,
      "sprout": 0,
      "timestamp": 1725842468,
      "transparent": 1400393419519498
    },
    {
      "height": 2656224,
      "lockbox": 0,
      "orchard": 49982685845416,
      "sapling": 97271320404512,
      "sprout": 0,
      "timestamp": 1727071884,
      "transparent": 1405816931250072
    },
    {
      "height": 2672441,
      "lockbox": 0,
      "orchard": 62916751565331,
      "sapling": 94102682220302,
      "sprout": 0,
      "timestamp": 1728293571,
      "transparent": 1401119316214367
    },
    {
      "height": 2688790,
      "lockbox": 0,
      "orchard": 65276366749400,
      "sapling": 96783831493650,
      "sprout": 0,
      "timestamp": 1729526489,
      "transparent": 1401187614256950
    },
    {
      "height": 2704869,
      "lockbox": 0,
      "orchard": 68827574130662,
      "sapling": 101680597997791,
      "sprout": 0,
      "timestamp": 1730737689,
      "transparent": 1397764327871547
    },
    {
      "height": 2721394,
      "lockbox": 0,
      "orchard": 67091241632824,
      "sapling": 100656381130961,
      "sprout": 0,
      "timestamp": 1731982786,
      "transparent": 1405688939736215
    },
    {
      "height": 2737710,
      "lockbox": 212081250000,
      "orchard": 70733276073147,
      "sapling": 102917836065389,
      "sprout": 0,
      "timestamp": 1733213851,
      "transparent": 1402904775361464
    },
    {
      "height": 2753928,
      "lockbox": 516168750000,
      "orchard": 74198836209043,
      "sapling": 102173142040216,
      "sprout": 0,
      "timestamp": 1734435628,
      "transparent": 1402413884250741
    },
    {
      "height": 2770350,
      "lockbox": 824081250000,
      "orchard": 93868900185178,
      "sapling": 98004906850701,
      "sprout": 0,
      "timestamp": 1735674367,
      "transparent": 1389170080464121
    },
    {
      "height": 2786580,
      "lockbox": 1128393750000,
      "orchard": 97808954458257,
      "sapling": 96896869644759,
      "sprout": 0,
      "timestamp": 1736897049,
      "transparent": 1388569688396984
    },
    {
      "height": 2802894,
      "lockbox": 1434281250000,
      "orchard": 101104984956458,
      "sapling": 85251356939264,
      "sprout": 0,
      "timestamp": 1738126233,
      "transparent": 1399162345604278
    },
    {
      "height": 2819041,
      "lockbox": 1737037500000,
      "orchard": 103174260065872,
      "sapling": 85439651022194,
      "sprout": 0,
      "timestamp": 1739343605,
      "transparent": 1399124988911934
    },
    {
      "height": 2835567,
      "lockbox": 2046900000000,
      "orchard": 116475205006793,
      "sapling": 86378812725383,
      "sprout": 0,
      "timestamp": 1740588845,
      "transparent": 1387157207267824
    },
    {
      "height": 2851632,
      "lockbox": 2348118750000,
      "orchard": 159103166246865,
      "sapling": 86233405568355,
      "sprout": 0,
      "timestamp": 1741800447,
      "transparent": 1346883590684780
    },
    {
      "height": 2867940,
      "lockbox": 2653893750000,
      "orchard": 173786340928476,
      "sapling": 88784940527122,
      "sprout": 0,
      "timestamp": 1743029063,
      "transparent": 1331891231044402
    },
    {
      "height": 2884297,
      "lockbox": 2960587500000,
      "orchard": 194453502609485,
      "sapling": 84505391976652,
      "sprout": 0,
      "timestamp": 1744262243,
      "transparent": 1317752705413863
    },
    {
      "height": 2900591,
      "lockbox": 3266100000000,
      "orchard": 191582800503075,
      "sapling": 82626207567385,
      "sprout": 0,
      "timestamp": 1745491268,
      "transparent": 1324743016929540
    },
    {
      "height": 2917081,
      "lockbox": 3575287500000,
      "orchard": 207419081928610,
      "sapling": 83997762152776,
      "sprout": 0,
      "timestamp": 1746733481,
      "transparent": 1309802555918614
    },
    {
      "height": 2933213,
      "lockbox": 3877762500000,
      "orchard": 218888177391028,
      "sapling": 82883381215161,
      "sprout": 0,
      "timestamp": 1747949795,
      "transparent": 1301665991393811
    },
    {
      "height": 2949596,
      "lockbox": 4184943750000,
      "orchard": 226757621139699,
      "sapling": 83060428244166,
      "sprout": 0,
      "timestamp": 1749183774,
      "transparent": 1295872163116135
    },
    {
      "height": 2965950,
      "lockbox": 4491581250000,
      "orchard": 228524533441697,
      "sapling": 83891463019782,
      "sprout": 0,
      "timestamp": 1750417030,
      "transparent": 1295522891038521
    },
    {
      "height": 2982263,
      "lockbox": 4797450000000,
      "orchard": 228585085940698,
      "sapling": 84249776942149,
      "sprout": 0,
      "timestamp": 1751647143,
      "transparent": 1297347062117153
    },
    {
      "height": 2998455,
      "lockbox": 5101050000000,
      "orchard": 229939157252670,
      "sapling": 84303731191499,
      "sprout": 0,
      "timestamp": 1752867377,
      "transparent": 1298165436555831
    },
    {
      "height": 3014865,
      "lockbox": 5408737500000,
      "orchard": 231306966072155,
      "sapling": 87220873445039,
      "sprout": 0,
      "timestamp": 1754103540,
      "transparent": 1296136860482806
    },
    {
      "height": 3031194,
      "lockbox": 5714906250000,
      "orchard": 266206740682083,
      "sapling": 87336774051187,
      "sprout": 0,
      "timestamp": 1755334693,
      "transparent": 1263366422766730
    },
    {
      "height": 3047385,
      "lockbox": 6018487500000,
      "orchard": 283474572739103,
      "sapling": 87389291678974,
      "sprout": 0,
      "timestamp": 1756553972,
      "transparent": 1248272335581923
    },
    {
      "height": 3063697,
      "lockbox": 6324337500000,
      "orchard": 292011265940684,
      "sapling": 85328854635926,
      "sprout": 0,
      "timestamp": 1757782755,
      "transparent": 1244038979423390
    },
    {
      "height": 3079876,
      "lockbox": 6627693750000,
      "orchard": 295217232844055,
      "sapling": 85381578876910,
      "sprout": 0,
      "timestamp": 1759002216,
      "transparent": 1243004900779035
    },
    {
      "height": 3096363,
      "lockbox": 6936825000000,
      "orchard": 339963537765358,
      "sapling": 78129405178791,
      "sprout": 0,
      "timestamp": 1760244046,
      "transparent": 1207777732055851
    },
    {
      "height": 3112356,
      "lockbox": 7236693750000,
      "orchard": 413009398188084,
      "sapling": 77360852217249,
      "sprout": 0,
      "timestamp": 1761448781,
      "transparent": 1137699462094667
    },
    {
      "height": 3128970,
      "lockbox": 7548206250000,
      "orchard": 411466102176295,
      "sapling": 70742426237680,
      "sprout": 0,
      "timestamp": 1762700619,
      "transparent": 1148145609086025
    },
    {
      "height": 3145155,
      "lockbox": 7851675000000,
      "orchard": 416095047283302,
      "sapling": 64670724009232,
      "sprout": 0,
      "timestamp": 1763920630,
      "transparent": 1151813803707466
    },
    {
      "height": 3161665,
      "lockbox": 286237500000,
      "orchard": 415400370182780,
      "sapling": 63966056668627,
      "sprout": 0,
      "timestamp": 1765164635,
      "transparent": 1163358273148593
    },
    {
      "height": 3177864,
      "lockbox": 589968750000,
      "orchard": 417303114312592,
      "sapling": 63574565465414,
      "sprout": 0,
      "timestamp": 1766385621,
      "transparent": 1164074382721994
    },
    {
      "height": 3194113,
      "lockbox": 894637500000,
      "orchard": 420880055561542,
      "sapling": 62736631939980,
      "sprout": 0,
      "timestamp": 1767610525,
      "transparent": 1163569612498478
    },
    {
      "height": 3210330,
      "lockbox": 1198706250000,
      "orchard": 429644456649178,
      "sapling": 62114839885232,
      "sprout": 0,
      "timestamp": 1768832757,
      "transparent": 1157656840965590
    },
    {
      "height": 3226770,
      "lockbox": 1506956250000,
      "orchard": 440098958543927,
      "sapling": 61747455602126,
      "sprout": 0,
      "timestamp": 1770071598,
      "transparent": 1149830223353947
    },
    {
      "height": 3243110,
      "lockbox": 1813331250000,
      "orchard": 438551911462588,
      "sapling": 61805929639846,
      "sprout": 0,
      "timestamp": 1771302274,
      "transparent": 1153565546397566
    },
    {
      "height": 3259485,
      "lockbox": 2120362500000,
      "orchard": 439616599742126,
      "sapling": 61852358050091,
      "sprout": 0,
      "timestamp": 1772536295,
      "transparent": 1154705992207783
    },
    {
      "height": 3275733,
      "lockbox": 2425012500000,
      "orchard": 451481336990988,
      "sapling": 61670130466952,
      "sprout": 0,
      "timestamp": 1773760514,
      "transparent": 1145257582542060
    },
    {
      "height": 3292111,
      "lockbox": 2732100000000,
      "orchard": 452780355940739,
      "sapling": 61260508892990,
      "sprout": 2542447009822,
      "timestamp": 1774994628,
      "transparent": 1144040229710929
    },
    {
      "height": 3308406,
      "lockbox": 3037631250000,
      "orchard": 454202933182309,
      "sapling": 60381681262272,
      "sprout": 2540941766914,
      "timestamp": 1776223450,
      "transparent": 1145738547842985
    },
    {
      "height": 3324713,
      "lockbox": 3343387500000,
      "orchard": 455084507811716,
      "sapling": 59827540234201,
      "sprout": 2540941766914,
      "timestamp": 1777451980,
      "transparent": 1147653326741649
    },
    {
      "height": 3341010,
      "lockbox": 3648956250000,
      "orchard": 454042517709135,
      "sapling": 59783129663088,
      "sprout": 2540941766914,
      "timestamp": 1778680789,
      "transparent": 1150980564915343
    },
    {
      "height": 3357313,
      "lockbox": 3954637500000,
      "orchard": 449470009161841,
      "sapling": 59319241115137,
      "sprout": 2540941766914,
      "timestamp": 1779909664,
      "transparent": 1158258624510588
    },
    {
      "height": 3373617,
      "lockbox": 4260337500000,
      "orchard": 392483866974711,
      "sapling": 58462502303331,
      "sprout": 2540941766914,
      "timestamp": 1781138380,
      "transparent": 1218343305509524
    },
    {
      "height": 3389285,
      "lockbox": 4554112500000,
      "orchard": 370126813637888,
      "sapling": 62130880912128,
      "sprout": 2540941766914,
      "timestamp": 1782319307,
      "transparent": 1239186330237550
    },
    {
      "height": 3389919,
      "lockbox": 4566000000000,
      "orchard": 370146099773602,
      "sapling": 62128357923379,
      "sprout": 2540941766914,
      "timestamp": 1782367113,
      "transparent": 1239256742090585
    },
    {
      "height": 3390433,
      "lockbox": 4575637500000,
      "orchard": 371266867323952,
      "sapling": 62128007801844,
      "sprout": 2540941766914,
      "timestamp": 1782405691,
      "transparent": 1238206999661770
    },
    {
      "height": 3391576,
      "lockbox": 4597068750000,
      "orchard": 377839154015992,
      "sapling": 62124671266506,
      "sprout": 2540941766914,
      "timestamp": 1782492138,
      "transparent": 1231795212005068
    },
    {
      "height": 3392718,
      "lockbox": 4618481250000,
      "orchard": 377735556192386,
      "sapling": 62140857456349,
      "sprout": 2540941766914,
      "timestamp": 1782578424,
      "transparent": 1232039648638831
    },
    {
      "height": 3393873,
      "lockbox": 4640137500000,
      "orchard": 377452772185665,
      "sapling": 62139385970438,
      "sprout": 2540941766914,
      "timestamp": 1782664827,
      "transparent": 1232482716631463
    },
    {
      "height": 3395009,
      "lockbox": 4661437500000,
      "orchard": 377112744065365,
      "sapling": 62145167924048,
      "sprout": 2540941766914,
      "timestamp": 1782751279,
      "transparent": 1232973162798153
    },
    {
      "height": 3396160,
      "lockbox": 4683018750000,
      "orchard": 377237212751668,
      "sapling": 62104916623064,
      "sprout": 2540941766914,
      "timestamp": 1782837742,
      "transparent": 1233047207912834
    },
    {
      "height": 3397307,
      "lockbox": 4704525000000,
      "orchard": 377354349110888,
      "sapling": 62086378193660,
      "sprout": 2540941766914,
      "timestamp": 1782924012,
      "transparent": 1233106322483018
    },
    {
      "height": 3398445,
      "lockbox": 4725862500000,
      "orchard": 376491969022707,
      "sapling": 62085925279049,
      "sprout": 2540941766914,
      "timestamp": 1783010500,
      "transparent": 1234125630485810
    },
    {
      "height": 3399600,
      "lockbox": 4747518750000,
      "orchard": 376485261063725,
      "sapling": 62072321624299,
      "sprout": 2540941766914,
      "timestamp": 1783096888,
      "transparent": 1234304754599542
    },
    {
      "height": 3400748,
      "lockbox": 4769043750000,
      "orchard": 376575468066714,
      "sapling": 62071632843248,
      "sprout": 2540941766914,
      "timestamp": 1783183337,
      "transparent": 1234373086377604
    },
    {
      "height": 3401898,
      "lockbox": 4790606250000,
      "orchard": 376778586761153,
      "sapling": 62033988162597,
      "sprout": 2540941766914,
      "timestamp": 1783269555,
      "transparent": 1234365737363816
    },
    {
      "height": 3403041,
      "lockbox": 4812037500000,
      "orchard": 376482818011207,
      "sapling": 61980733278679,
      "sprout": 2540941766914,
      "timestamp": 1783356138,
      "transparent": 1234871923497680
    },
    {
      "height": 3404188,
      "lockbox": 4833543750000,
      "orchard": 376603395240825,
      "sapling": 62013556467679,
      "sprout": 2540941766914,
      "timestamp": 1783442467,
      "transparent": 1234876235579062
    },
    {
      "height": 3405332,
      "lockbox": 4854993750000,
      "orchard": 376452856010662,
      "sapling": 59266731859861,
      "sprout": 2540941766914,
      "timestamp": 1783528803,
      "transparent": 1237930899417043
    },
    {
      "height": 3406225,
      "lockbox": 4871737500000,
      "orchard": 376478300868422,
      "sapling": 59253651823579,
      "sprout": 2540941766914,
      "timestamp": 1783595876,
      "transparent": 1238041322095565
    },
    {
      "height": 3406489,
      "lockbox": 4876687500000,
      "orchard": 376536131174658,
      "sapling": 59277449106941,
      "sprout": 2540941766914,
      "timestamp": 1783615265,
      "transparent": 1237995994505967
    },
    {
      "height": 3407623,
      "lockbox": 4897950000000,
      "orchard": 376770707191428,
      "sapling": 59460392597456,
      "sprout": 2540941766914,
      "timestamp": 1783701688,
      "transparent": 1237734399998682
    },
    {
      "height": 3408777,
      "lockbox": 4919587500000,
      "orchard": 376283098938916,
      "sapling": 59360740122186,
      "sprout": 2540941766914,
      "timestamp": 1783788024,
      "transparent": 1238480335726464
    },
    {
      "height": 3409923,
      "lockbox": 4941075000000,
      "orchard": 376850776609813,
      "sapling": 59367710398243,
      "sprout": 2540941766914,
      "timestamp": 1783874535,
      "transparent": 1238063262779510
    },
    {
      "height": 3411071,
      "lockbox": 4962600000000,
      "orchard": 377117473936966,
      "sapling": 59343956669405,
      "sprout": 2540941766914,
      "timestamp": 1783960797,
      "transparent": 1237978169181195
    },
    {
      "height": 3412209,
      "lockbox": 4983937500000,
      "orchard": 377022796626381,
      "sapling": 59334295091714,
      "sprout": 2540941766914,
      "timestamp": 1784047249,
      "transparent": 1238238983069471
    },
    {
      "height": 3413368,
      "lockbox": 5005668750000,
      "orchard": 376810394662329,
      "sapling": 59365768195394,
      "sprout": 2540941766914,
      "timestamp": 1784133740,
      "transparent": 1238579274429843
    },
    {
      "height": 3414509,
      "lockbox": 5027062500000,
      "orchard": 376780321262333,
      "sapling": 59307560741793,
      "sprout": 2540941766914,
      "timestamp": 1784220061,
      "transparent": 1238824442783440
    },
    {
      "height": 3415656,
      "lockbox": 5048568750000,
      "orchard": 376304414707173,
      "sapling": 59095984602772,
      "sprout": 2540941766914,
      "timestamp": 1784306451,
      "transparent": 1239669637977621
    },
    {
      "height": 3416814,
      "lockbox": 5070281250000,
      "orchard": 376879955605383,
      "sapling": 59058208215199,
      "sprout": 2540941766914,
      "timestamp": 1784392886,
      "transparent": 1239291098466984
    },
    {
      "height": 3417944,
      "lockbox": 5091468750000,
      "orchard": 376840441245437,
      "sapling": 59058169242303,
      "sprout": 2540941766914,
      "timestamp": 1784479345,
      "transparent": 1239486026799826
    },
    {
      "height": 3419099,
      "lockbox": 5113125000000,
      "orchard": 377085290922892,
      "sapling": 59071557369306,
      "sprout": 2540941766914,
      "timestamp": 1784565527,
      "transparent": 1239386601495368
    },
    {
      "height": 3420243,
      "lockbox": 5134575000000,
      "orchard": 378466046275188,
      "sapling": 59098012904630,
      "sprout": 2540941766914,
      "timestamp": 1784652140,
      "transparent": 1238136690607748
    },
    {
      "height": 3421396,
      "lockbox": 5156193750000,
      "orchard": 378307880418099,
      "sapling": 58988776301512,
      "sprout": 2540941766914,
      "timestamp": 1784738452,
      "transparent": 1238562630567955
    },
    {
      "height": 3422539,
      "lockbox": 5177625000000,
      "orchard": 376707246133301,
      "sapling": 59038877602314,
      "sprout": 2540891821914,
      "timestamp": 1784824508,
      "transparent": 1240270375996951
    },
    {
      "height": 3422540,
      "lockbox": 5177643750000,
      "orchard": 376706435728846,
      "sapling": 59029092824057,
      "sprout": 2540891821914,
      "timestamp": 1784824784,
      "transparent": 1240281108679663
    }
  ],
  "ironwood_history": [],
  "methodology": {
    "flow_note": "Snapshot differences and valueDeltaZat are net pool changes, not provable gross inflow/outflow or destinations.",
    "gross_flows_available": false,
    "ironwood_state": "pending_activation",
    "primary_focus": "sapling + orchard + ironwood",
    "shielded_definition": "sprout + sapling + orchard + ironwood"
  },
  "network": "main",
  "pools": {
    "ironwood": {
      "active": false,
      "balance_zatoshis": null,
      "flow_semantics": "not_available",
      "last_error": null,
      "monitored": false,
      "net_change_24h_bps": null,
      "net_change_24h_zatoshis": null,
      "net_change_7d_bps": null,
      "net_change_7d_zatoshis": null,
      "net_change_since_activation_zatoshis": null,
      "source": null,
      "status": "pending_activation",
      "supply_share_bps": null,
      "supported": false,
      "tree_present": false
    },
    "orchard": {
      "balance_zatoshis": 376706435728846,
      "flow_semantics": "net_balance_change",
      "net_change_24h_bps": -4649,
      "net_change_24h_zatoshis": -1759610546342,
      "net_change_7d_bps": -276,
      "net_change_7d_zatoshis": -103958933483,
      "net_change_since_activation_zatoshis": null,
      "shielded_share_bps": 859518,
      "supply_share_bps": 223733
    },
    "sapling": {
      "balance_zatoshis": 59029092824057,
      "flow_semantics": "net_balance_change",
      "net_change_24h_bps": -1166,
      "net_change_24h_zatoshis": -68920080573,
      "net_change_7d_bps": -5671,
      "net_change_7d_zatoshis": -336675371337,
      "net_change_since_activation_zatoshis": null,
      "shielded_share_bps": 134685,
      "supply_share_bps": 35058
    }
  },
  "project": {
    "focus": [
      "sapling",
      "orchard",
      "ironwood"
    ],
    "name": "Zcash Shielded Observatory"
  },
  "schema_version": 2,
  "sources": [
    {
      "id": "zcashinfo",
      "public": true,
      "role": "supply_and_history",
      "status": "available"
    },
    {
      "id": "zebra_rpc",
      "public": false,
      "role": "ironwood_primary",
      "status": "not_configured"
    }
  ],
  "supply": {
    "accounting_difference_zatoshis": 0,
    "legacy_sprout_zatoshis": 2540891821914,
    "lockbox_zatoshis": 5177643750000,
    "net_change_24h_bps": -4155,
    "net_change_24h_zatoshis": -1828580571915,
    "net_change_7d_zatoshis": -440684249820,
    "shielded_share_bps": 260300,
    "shielded_zatoshis": 438276420374817,
    "total_zatoshis": 1683735172804480,
    "transparent_net_change_24h_bps": 1732,
    "transparent_net_change_24h_zatoshis": 2144418071915,
    "transparent_net_change_7d_bps": 1374,
    "transparent_net_change_7d_zatoshis": 1701834249820,
    "transparent_share_bps": 736625,
    "transparent_zatoshis": 1240281108679663
  }
}
